ampel/abstract/AbsBufferComplement.py
ampel/abstract/AbsChannelTemplate.py
ampel/abstract/AbsCompiler.py
ampel/abstract/AbsConfigMorpher.py
ampel/abstract/AbsConfigUpdater.py
ampel/abstract/AbsDocIngester.py
ampel/abstract/AbsDocUpdater.py
ampel/abstract/AbsEventUnit.py
ampel/abstract/AbsOpsUnit.py
ampel/abstract/AbsProcessController.py
ampel/abstract/AbsT0Muxer.py
ampel/abstract/AbsT3Filter.py
ampel/abstract/AbsT3Loader.py
ampel/abstract/AbsT3Projector.py
ampel/abstract/AbsT3Selector.py
ampel/abstract/AbsT3Stager.py
ampel/abstract/AbsT3Supplier.py
ampel/abstract/AbsT4ControlUnit.py
ampel/abstract/AbsTargetSource.py
ampel/abstract/AbsUnitResultAdapter.py
ampel/abstract/AbsWorker.py
ampel/abstract/README.md
ampel/aux/ComboDictModifier.py
ampel/aux/SimpleTagFilter.py
ampel/aux/filter/AbsLogicOperatorFilter.py
ampel/aux/filter/FlatDictArrayFilter.py
ampel/aux/filter/PrimitiveTypeArrayFilter.py
ampel/aux/filter/SimpleDictArrayFilter.py
ampel/cli/AbsCoreCommand.py
ampel/cli/AbsLoadCommand.py
ampel/cli/AbsStockCommand.py
ampel/cli/BufferCommand.py
ampel/cli/ConfigCommand.py
ampel/cli/DBCommand.py
ampel/cli/EventCommand.py
ampel/cli/JobCommand.py
ampel/cli/LogCommand.py
ampel/cli/ProcessCommand.py
ampel/cli/RunCommand.py
ampel/cli/StartCommand.py
ampel/cli/T2Command.py
ampel/cli/T3BufferExporterStager.py
ampel/cli/T3BufferExporterUnit.py
ampel/cli/ViewCommand.py
ampel/cli/export.py
ampel/cli/utils.py
ampel/config/ScheduleEvaluator.py
ampel/config/alter/HashT2Config.py
ampel/config/alter/ResolveRunTimeAliases.py
ampel/config/builder/BaseConfigChecker.py
ampel/config/builder/ConfigBuilder.py
ampel/config/builder/ConfigChecker.py
ampel/config/builder/ConfigValidator.py
ampel/config/builder/DisplayOptions.py
ampel/config/builder/DistConfigBuilder.py
ampel/config/builder/FirstPassConfig.py
ampel/config/builder/ProcessMorpher.py
ampel/config/builder/get_env.py
ampel/config/collector/AbsDictConfigCollector.py
ampel/config/collector/AbsForwardConfigCollector.py
ampel_core-0.10.4.post0.dist-info/LICENSE
ampel_core-0.10.4.post0.dist-info/METADATA
ampel_core-0.10.4.post0.dist-info/WHEEL
ampel_core-0.10.4.post0.dist-info/entry_points.txt
ampel_core-0.10.4.post0.dist-info/RECORD
