Metadata-Version: 2.1
Name: ampel-core
Version: 0.10.4.post0
Summary: Alice in Modular Provenance-Enabled Land
Home-page: https://ampelproject.github.io
License: BSD-3-Clause
Author: Valery Brinnel
Maintainer: Jakob van Santen
Maintainer-email: jakob.van.santen@desy.de
Requires-Python: >=3.10,<4.0
Classifier: Development Status :: 4 - Beta
Classifier: Intended Audience :: Science/Research
Classifier: License :: OSI Approved :: BSD License
Classifier: Programming Language :: Python :: 3
Classifier: Programming Language :: Python :: 3.10
Classifier: Programming Language :: Python :: 3.11
Classifier: Programming Language :: Python :: 3.12
Classifier: Topic :: Scientific/Engineering :: Information Analysis
Classifier: Typing :: Typed
Provides-Extra: encrypted-secrets
Provides-Extra: server
Provides-Extra: slack
Provides-Extra: transform
Requires-Dist: ampel-interface (>=0.10.4,<0.11)
Requires-Dist: fastapi (>=0.95) ; extra == "server"
Requires-Dist: prometheus-client (>=0.16)
Requires-Dist: psutil (>=6.0.0,<7.0.0)
Requires-Dist: pymongo (>=4.0,<5.0)
Requires-Dist: schedule (>=1.0.0,<2.0.0)
Requires-Dist: setproctitle (>=1.3.3,<2.0.0) ; extra == "server"
Requires-Dist: sjcl (>=0.2.1,<0.3.0) ; extra == "encrypted-secrets"
Requires-Dist: slack-sdk (>=3.18.1,<4.0.0) ; extra == "slack"
Requires-Dist: uvicorn[standard] (>=0.21.1) ; extra == "server"
Requires-Dist: xxhash (>=3.0.0,<4.0.0)
Requires-Dist: yq (>=3.0.0,<4.0.0) ; extra == "transform"
Project-URL: Documentation, https://ampelproject.github.io/Ampel-core
Project-URL: Repository, https://github.com/AmpelProject/Ampel-core
